[
  [
    {
      "x": 380,
      "y": 123,
      "t": 1713415375.1447673
    },
    {
      "x": 378,
      "y": 122,
      "t": 1713415375.1497705
    },
    {
      "x": 377,
      "y": 122,
      "t": 1713415375.1517699
    },
    {
      "x": 374,
      "y": 122,
      "t": 1713415375.1587665
    },
    {
      "x": 373,
      "y": 122,
      "t": 1713415375.1637673
    },
    {
      "x": 371,
      "y": 122,
      "t": 1713415375.1647687
    },
    {
      "x": 370,
      "y": 122,
      "t": 1713415375.1667695
    },
    {
      "x": 369,
      "y": 122,
      "t": 1713415375.1677682
    },
    {
      "x": 368,
      "y": 122,
      "t": 1713415375.168769
    },
    {
      "x": 367,
      "y": 122,
      "t": 1713415375.1707685
    },
    {
      "x": 366,
      "y": 122,
      "t": 1713415375.1727686
    },
    {
      "x": 365,
      "y": 122,
      "t": 1713415375.1747713
    },
    {
      "x": 364,
      "y": 122,
      "t": 1713415375.1767673
    },
    {
      "x": 363,
      "y": 122,
      "t": 1713415375.178769
    },
    {
      "x": 362,
      "y": 122,
      "t": 1713415375.1797671
    },
    {
      "x": 361,
      "y": 123,
      "t": 1713415375.1817672
    },
    {
      "x": 360,
      "y": 123,
      "t": 1713415375.1837668
    },
    {
      "x": 358,
      "y": 124,
      "t": 1713415375.1847699
    },
    {
      "x": 357,
      "y": 124,
      "t": 1713415375.1867712
    },
    {
      "x": 355,
      "y": 124,
      "t": 1713415375.1877692
    },
    {
      "x": 355,
      "y": 125,
      "t": 1713415375.1917696
    },
    {
      "x": 354,
      "y": 125,
      "t": 1713415375.1947684
    },
    {
      "x": 350,
      "y": 125,
      "t": 1713415375.1957684
    },
    {
      "x": 350,
      "y": 126,
      "t": 1713415375.1967683
    },
    {
      "x": 349,
      "y": 126,
      "t": 1713415375.1987693
    },
    {
      "x": 348,
      "y": 127,
      "t": 1713415375.2007673
    },
    {
      "x": 346,
      "y": 127,
      "t": 1713415375.2027674
    },
    {
      "x": 344,
      "y": 128,
      "t": 1713415375.2037706
    },
    {
      "x": 342,
      "y": 128,
      "t": 1713415375.2057679
    },
    {
      "x": 341,
      "y": 129,
      "t": 1713415375.2067666
    },
    {
      "x": 340,
      "y": 130,
      "t": 1713415375.2077665
    },
    {
      "x": 338,
      "y": 130,
      "t": 1713415375.2097666
    },
    {
      "x": 336,
      "y": 131,
      "t": 1713415375.2107675
    },
    {
      "x": 335,
      "y": 131,
      "t": 1713415375.212769
    },
    {
      "x": 334,
      "y": 132,
      "t": 1713415375.2147694
    },
    {
      "x": 333,
      "y": 133,
      "t": 1713415375.2167685
    },
    {
      "x": 332,
      "y": 133,
      "t": 1713415375.2177696
    },
    {
      "x": 331,
      "y": 133,
      "t": 1713415375.219769
    },
    {
      "x": 329,
      "y": 134,
      "t": 1713415375.2207687
    },
    {
      "x": 327,
      "y": 135,
      "t": 1713415375.2227685
    },
    {
      "x": 325,
      "y": 136,
      "t": 1713415375.2247694
    },
    {
      "x": 323,
      "y": 136,
      "t": 1713415375.225769
    },
    {
      "x": 323,
      "y": 137,
      "t": 1713415375.2267687
    },
    {
      "x": 322,
      "y": 137,
      "t": 1713415375.2277694
    },
    {
      "x": 321,
      "y": 138,
      "t": 1713415375.22877
    },
    {
      "x": 320,
      "y": 138,
      "t": 1713415375.230769
    },
    {
      "x": 319,
      "y": 138,
      "t": 1713415375.2317672
    },
    {
      "x": 319,
      "y": 139,
      "t": 1713415375.232769
    },
    {
      "x": 318,
      "y": 139,
      "t": 1713415375.234772
    },
    {
      "x": 316,
      "y": 140,
      "t": 1713415375.234772
    },
    {
      "x": 315,
      "y": 141,
      "t": 1713415375.235771
    },
    {
      "x": 314,
      "y": 141,
      "t": 1713415375.2367694
    },
    {
      "x": 314,
      "y": 142,
      "t": 1713415375.2387676
    },
    {
      "x": 313,
      "y": 142,
      "t": 1713415375.2397723
    },
    {
      "x": 312,
      "y": 142,
      "t": 1713415375.2417686
    },
    {
      "x": 310,
      "y": 144,
      "t": 1713415375.2437677
    },
    {
      "x": 309,
      "y": 145,
      "t": 1713415375.2437677
    },
    {
      "x": 308,
      "y": 145,
      "t": 1713415375.2457697
    },
    {
      "x": 307,
      "y": 146,
      "t": 1713415375.2477694
    },
    {
      "x": 306,
      "y": 146,
      "t": 1713415375.2477694
    },
    {
      "x": 305,
      "y": 147,
      "t": 1713415375.248772
    },
    {
      "x": 304,
      "y": 148,
      "t": 1713415375.2497723
    },
    {
      "x": 303,
      "y": 149,
      "t": 1713415375.2517695
    },
    {
      "x": 301,
      "y": 150,
      "t": 1713415375.2547712
    },
    {
      "x": 300,
      "y": 151,
      "t": 1713415375.2557693
    },
    {
      "x": 299,
      "y": 152,
      "t": 1713415375.25677
    },
    {
      "x": 299,
      "y": 153,
      "t": 1713415375.2577677
    },
    {
      "x": 298,
      "y": 153,
      "t": 1713415375.2597678
    },
    {
      "x": 298,
      "y": 154,
      "t": 1713415375.2617717
    },
    {
      "x": 297,
      "y": 155,
      "t": 1713415375.2627695
    },
    {
      "x": 296,
      "y": 155,
      "t": 1713415375.2637696
    },
    {
      "x": 295,
      "y": 156,
      "t": 1713415375.264769
    },
    {
      "x": 295,
      "y": 157,
      "t": 1713415375.2657692
    },
    {
      "x": 294,
      "y": 157,
      "t": 1713415375.2667694
    },
    {
      "x": 294,
      "y": 158,
      "t": 1713415375.2687693
    },
    {
      "x": 292,
      "y": 160,
      "t": 1713415375.2697704
    },
    {
      "x": 291,
      "y": 161,
      "t": 1713415375.2707698
    },
    {
      "x": 291,
      "y": 162,
      "t": 1713415375.2717688
    },
    {
      "x": 290,
      "y": 163,
      "t": 1713415375.2727695
    },
    {
      "x": 290,
      "y": 164,
      "t": 1713415375.27377
    },
    {
      "x": 288,
      "y": 165,
      "t": 1713415375.2757692
    },
    {
      "x": 288,
      "y": 166,
      "t": 1713415375.2767708
    },
    {
      "x": 288,
      "y": 167,
      "t": 1713415375.2777715
    },
    {
      "x": 287,
      "y": 167,
      "t": 1713415375.278772
    },
    {
      "x": 287,
      "y": 169,
      "t": 1713415375.2797701
    },
    {
      "x": 286,
      "y": 170,
      "t": 1713415375.2807705
    },
    {
      "x": 286,
      "y": 171,
      "t": 1713415375.2837706
    },
    {
      "x": 285,
      "y": 172,
      "t": 1713415375.2847703
    },
    {
      "x": 284,
      "y": 173,
      "t": 1713415375.2867694
    },
    {
      "x": 284,
      "y": 174,
      "t": 1713415375.2867694
    },
    {
      "x": 283,
      "y": 176,
      "t": 1713415375.2887697
    },
    {
      "x": 283,
      "y": 177,
      "t": 1713415375.2907696
    },
    {
      "x": 283,
      "y": 179,
      "t": 1713415375.2917693
    },
    {
      "x": 282,
      "y": 179,
      "t": 1713415375.2927692
    },
    {
      "x": 282,
      "y": 180,
      "t": 1713415375.2937682
    },
    {
      "x": 282,
      "y": 181,
      "t": 1713415375.2947695
    },
    {
      "x": 281,
      "y": 182,
      "t": 1713415375.2957702
    },
    {
      "x": 281,
      "y": 184,
      "t": 1713415375.2977698
    },
    {
      "x": 281,
      "y": 185,
      "t": 1713415375.29877
    },
    {
      "x": 281,
      "y": 186,
      "t": 1713415375.2997696
    },
    {
      "x": 280,
      "y": 188,
      "t": 1713415375.3007703
    },
    {
      "x": 280,
      "y": 189,
      "t": 1713415375.3017724
    },
    {
      "x": 280,
      "y": 190,
      "t": 1713415375.3037698
    },
    {
      "x": 280,
      "y": 191,
      "t": 1713415375.3047698
    },
    {
      "x": 280,
      "y": 192,
      "t": 1713415375.3057702
    },
    {
      "x": 280,
      "y": 193,
      "t": 1713415375.3067698
    },
    {
      "x": 280,
      "y": 194,
      "t": 1713415375.3087697
    },
    {
      "x": 280,
      "y": 195,
      "t": 1713415375.3097703
    },
    {
      "x": 280,
      "y": 196,
      "t": 1713415375.3107703
    },
    {
      "x": 280,
      "y": 197,
      "t": 1713415375.31177
    },
    {
      "x": 280,
      "y": 198,
      "t": 1713415375.31377
    },
    {
      "x": 280,
      "y": 199,
      "t": 1713415375.3147693
    },
    {
      "x": 280,
      "y": 200,
      "t": 1713415375.31577
    },
    {
      "x": 280,
      "y": 201,
      "t": 1713415375.3167706
    },
    {
      "x": 280,
      "y": 202,
      "t": 1713415375.31777
    },
    {
      "x": 280,
      "y": 203,
      "t": 1713415375.3187692
    },
    {
      "x": 280,
      "y": 204,
      "t": 1713415375.32077
    },
    {
      "x": 280,
      "y": 206,
      "t": 1713415375.32377
    },
    {
      "x": 281,
      "y": 206,
      "t": 1713415375.32477
    },
    {
      "x": 281,
      "y": 207,
      "t": 1713415375.3257701
    },
    {
      "x": 281,
      "y": 208,
      "t": 1713415375.3277695
    },
    {
      "x": 282,
      "y": 209,
      "t": 1713415375.3287709
    },
    {
      "x": 282,
      "y": 210,
      "t": 1713415375.329771
    },
    {
      "x": 283,
      "y": 210,
      "t": 1713415375.3307698
    },
    {
      "x": 283,
      "y": 211,
      "t": 1713415375.3317692
    },
    {
      "x": 283,
      "y": 212,
      "t": 1713415375.3327696
    },
    {
      "x": 284,
      "y": 212,
      "t": 1713415375.3337705
    },
    {
      "x": 284,
      "y": 213,
      "t": 1713415375.3347702
    },
    {
      "x": 285,
      "y": 214,
      "t": 1713415375.3367698
    },
    {
      "x": 286,
      "y": 215,
      "t": 1713415375.3377697
    },
    {
      "x": 287,
      "y": 216,
      "t": 1713415375.3387704
    },
    {
      "x": 287,
      "y": 217,
      "t": 1713415375.34077
    },
    {
      "x": 288,
      "y": 217,
      "t": 1713415375.3417702
    },
    {
      "x": 288,
      "y": 218,
      "t": 1713415375.3427703
    },
    {
      "x": 289,
      "y": 218,
      "t": 1713415375.343772
    },
    {
      "x": 290,
      "y": 219,
      "t": 1713415375.3447735
    },
    {
      "x": 291,
      "y": 220,
      "t": 1713415375.3467703
    },
    {
      "x": 292,
      "y": 221,
      "t": 1713415375.3477707
    },
    {
      "x": 293,
      "y": 221,
      "t": 1713415375.3487704
    },
    {
      "x": 293,
      "y": 222,
      "t": 1713415375.34977
    },
    {
      "x": 294,
      "y": 222,
      "t": 1713415375.3507707
    },
    {
      "x": 294,
      "y": 223,
      "t": 1713415375.3517714
    },
    {
      "x": 295,
      "y": 223,
      "t": 1713415375.3527734
    },
    {
      "x": 296,
      "y": 224,
      "t": 1713415375.3537695
    },
    {
      "x": 298,
      "y": 225,
      "t": 1713415375.3547704
    },
    {
      "x": 299,
      "y": 225,
      "t": 1713415375.35677
    },
    {
      "x": 299,
      "y": 226,
      "t": 1713415375.3577707
    },
    {
      "x": 300,
      "y": 226,
      "t": 1713415375.3587704
    },
    {
      "x": 301,
      "y": 227,
      "t": 1713415375.3597708
    },
    {
      "x": 302,
      "y": 227,
      "t": 1713415375.3607707
    },
    {
      "x": 304,
      "y": 228,
      "t": 1713415375.36177
    },
    {
      "x": 304,
      "y": 229,
      "t": 1713415375.3627696
    },
    {
      "x": 305,
      "y": 229,
      "t": 1713415375.3637693
    },
    {
      "x": 307,
      "y": 230,
      "t": 1713415375.3647733
    },
    {
      "x": 307,
      "y": 231,
      "t": 1713415375.3657696
    },
    {
      "x": 309,
      "y": 231,
      "t": 1713415375.366771
    },
    {
      "x": 310,
      "y": 232,
      "t": 1713415375.3677707
    },
    {
      "x": 311,
      "y": 232,
      "t": 1713415375.3687706
    },
    {
      "x": 312,
      "y": 233,
      "t": 1713415375.3697705
    },
    {
      "x": 313,
      "y": 233,
      "t": 1713415375.3717706
    },
    {
      "x": 315,
      "y": 234,
      "t": 1713415375.3727708
    },
    {
      "x": 316,
      "y": 234,
      "t": 1713415375.3737705
    },
    {
      "x": 317,
      "y": 235,
      "t": 1713415375.3747709
    },
    {
      "x": 318,
      "y": 235,
      "t": 1713415375.3757708
    },
    {
      "x": 319,
      "y": 236,
      "t": 1713415375.3767688
    },
    {
      "x": 321,
      "y": 236,
      "t": 1713415375.3787723
    },
    {
      "x": 322,
      "y": 237,
      "t": 1713415375.3797715
    },
    {
      "x": 323,
      "y": 237,
      "t": 1713415375.3807704
    },
    {
      "x": 324,
      "y": 238,
      "t": 1713415375.3817725
    },
    {
      "x": 325,
      "y": 238,
      "t": 1713415375.3817725
    },
    {
      "x": 327,
      "y": 238,
      "t": 1713415375.3827705
    },
    {
      "x": 328,
      "y": 239,
      "t": 1713415375.3837702
    },
    {
      "x": 329,
      "y": 240,
      "t": 1713415375.3847704
    },
    {
      "x": 330,
      "y": 240,
      "t": 1713415375.385772
    },
    {
      "x": 332,
      "y": 240,
      "t": 1713415375.3867714
    },
    {
      "x": 333,
      "y": 240,
      "t": 1713415375.3877707
    },
    {
      "x": 334,
      "y": 241,
      "t": 1713415375.3887708
    },
    {
      "x": 335,
      "y": 241,
      "t": 1713415375.3897707
    },
    {
      "x": 336,
      "y": 242,
      "t": 1713415375.3907704
    },
    {
      "x": 337,
      "y": 242,
      "t": 1713415375.39177
    },
    {
      "x": 339,
      "y": 242,
      "t": 1713415375.3927708
    },
    {
      "x": 340,
      "y": 242,
      "t": 1713415375.3937705
    },
    {
      "x": 341,
      "y": 242,
      "t": 1713415375.394772
    },
    {
      "x": 343,
      "y": 243,
      "t": 1713415375.3957708
    },
    {
      "x": 345,
      "y": 243,
      "t": 1713415375.3967707
    },
    {
      "x": 347,
      "y": 244,
      "t": 1713415375.3977711
    },
    {
      "x": 348,
      "y": 244,
      "t": 1713415375.3987706
    },
    {
      "x": 349,
      "y": 244,
      "t": 1713415375.399771
    },
    {
      "x": 351,
      "y": 244,
      "t": 1713415375.4017723
    },
    {
      "x": 354,
      "y": 245,
      "t": 1713415375.4037707
    },
    {
      "x": 355,
      "y": 245,
      "t": 1713415375.4047709
    },
    {
      "x": 356,
      "y": 245,
      "t": 1713415375.405771
    },
    {
      "x": 358,
      "y": 246,
      "t": 1713415375.4078205
    },
    {
      "x": 360,
      "y": 246,
      "t": 1713415375.408771
    },
    {
      "x": 362,
      "y": 246,
      "t": 1713415375.4107692
    },
    {
      "x": 363,
      "y": 246,
      "t": 1713415375.4117715
    },
    {
      "x": 364,
      "y": 246,
      "t": 1713415375.4127712
    },
    {
      "x": 365,
      "y": 246,
      "t": 1713415375.414772
    },
    {
      "x": 366,
      "y": 246,
      "t": 1713415375.4157715
    },
    {
      "x": 367,
      "y": 246,
      "t": 1713415375.4167712
    },
    {
      "x": 368,
      "y": 246,
      "t": 1713415375.4177713
    },
    {
      "x": 369,
      "y": 246,
      "t": 1713415375.4187717
    },
    {
      "x": 370,
      "y": 246,
      "t": 1713415375.4197707
    },
    {
      "x": 371,
      "y": 246,
      "t": 1713415375.4217713
    },
    {
      "x": 373,
      "y": 246,
      "t": 1713415375.4227712
    },
    {
      "x": 374,
      "y": 246,
      "t": 1713415375.424771
    },
    {
      "x": 375,
      "y": 246,
      "t": 1713415375.425773
    },
    {
      "x": 376,
      "y": 246,
      "t": 1713415375.426771
    },
    {
      "x": 377,
      "y": 246,
      "t": 1713415375.4287713
    },
    {
      "x": 378,
      "y": 246,
      "t": 1713415375.4297714
    },
    {
      "x": 379,
      "y": 246,
      "t": 1713415375.4307718
    },
    {
      "x": 380,
      "y": 246,
      "t": 1713415375.4327703
    },
    {
      "x": 381,
      "y": 246,
      "t": 1713415375.4337742
    },
    {
      "x": 382,
      "y": 246,
      "t": 1713415375.4367716
    },
    {
      "x": 383,
      "y": 246,
      "t": 1713415375.4377708
    },
    {
      "x": 383,
      "y": 245,
      "t": 1713415375.4387712
    },
    {
      "x": 384,
      "y": 245,
      "t": 1713415375.439771
    },
    {
      "x": 385,
      "y": 245,
      "t": 1713415375.4417727
    },
    {
      "x": 386,
      "y": 245,
      "t": 1713415375.4437714
    },
    {
      "x": 387,
      "y": 244,
      "t": 1713415375.4447713
    },
    {
      "x": 388,
      "y": 244,
      "t": 1713415375.4467714
    },
    {
      "x": 389,
      "y": 244,
      "t": 1713415375.4497724
    },
    {
      "x": 390,
      "y": 243,
      "t": 1713415375.4517715
    },
    {
      "x": 391,
      "y": 243,
      "t": 1713415375.4527712
    },
    {
      "x": 392,
      "y": 243,
      "t": 1713415375.4547715
    },
    {
      "x": 392,
      "y": 242,
      "t": 1713415375.4577706
    },
    {
      "x": 393,
      "y": 242,
      "t": 1713415375.4587708
    },
    {
      "x": 394,
      "y": 241,
      "t": 1713415375.4607708
    },
    {
      "x": 395,
      "y": 241,
      "t": 1713415375.4627717
    },
    {
      "x": 396,
      "y": 240,
      "t": 1713415375.467772
    },
    {
      "x": 397,
      "y": 240,
      "t": 1713415375.4727716
    },
    {
      "x": 397,
      "y": 239,
      "t": 1713415375.4747713
    },
    {
      "x": 398,
      "y": 239,
      "t": 1713415375.4807718
    },
    {
      "x": 398,
      "y": 238,
      "t": 1713415375.4817712
    },
    {
      "x": 398,
      "y": 237,
      "t": 1713415375.4867718
    },
    {
      "x": 398,
      "y": 236,
      "t": 1713415375.4957714
    },
    {
      "x": 398,
      "y": 235,
      "t": 1713415375.5057719
    }
  ]
]
